[
  {
    "__tag": "Knowledge",
    "id": "105f027b-9efb-4032-a6ae-c145d78b8409",
    "content": "あ",
    "authorId": "test-author",
    "createdAt": 1753004286,
    "updatedAt": 1753004286
  },
  {
    "__tag": "Knowledge",
    "id": "fd7515ef-be4f-4abe-845b-1c960b80c9bc",
    "content": "テスト",
    "authorId": "test-author",
    "createdAt": 1753060929,
    "updatedAt": 1753060929
  },
  {
    "__tag": "Knowledge",
    "id": "e918ee1c-c899-4c94-8de1-b542f6615548",
    "content": "あかさたな",
    "authorId": "text-auther",
    "createdAt": 1753060955,
    "updatedAt": 1753060955
  },
  {
    "__tag": "Knowledge",
    "id": "c82f97d9-6de6-4973-8457-524a9f52e531",
    "content": "編集後",
    "authorId": "text-auther",
    "createdAt": 1753062864,
    "updatedAt": 1753063755
  }
]